{
  "project_info": {
    "project_number": "1017975523775",
    "project_id": "smpnt-projects",
    "storage_bucket": "smpnt-projects.appspot.com"
  },
  "client": [
    {
      "client_info": {
        "mobilesdk_app_id": "1:1017975523775:android:2babc3e9b329faf7c3390a",
        "android_client_info": {
          "package_name": "smpnt.com.ecommerce"
        }
      },
      "oauth_client": [
        {
          "client_id": "1017975523775-5qhf9lookc6g8a0issh4lrm6hggvsuk0.apps.googleusercontent.com",
          "client_type": 3
        }
      ],
      "api_key": [
        {
          "current_key": "AIzaSyCeIPnk_6ObHgAhwi4vIq6yQTpl5_10zmw"
        }
      ],
      "services": {
        "appinvite_service": {
          "other_platform_oauth_client": [
            {
              "client_id": "1017975523775-5qhf9lookc6g8a0issh4lrm6hggvsuk0.apps.googleusercontent.com",
              "client_type": 3
            }
          ]
        }
      }
    }
  ],
  "configuration_version": "1"
}